setup.py
bin/tumblr
teblr/__init__.py
teblr/console.py
teblr/helpers.py
teblr.egg-info/PKG-INFO
teblr.egg-info/SOURCES.txt
teblr.egg-info/dependency_links.txt
teblr.egg-info/requires.txt
teblr.egg-info/top_level.txt