Metadata-Version: 1.0
Name: teblr
Version: 0.0.3
Summary: Tumblr on command line
Home-page: http://nvijaykumar.me/teblr/
Author: Vijay Kumar
Author-email: nvijaykumar2012@gmail.com
License: Apache 2.0
Keywords: tumblr terminal commandline blogging linux
Platform: UNKNOWN
